MANIFEST.in
README.md
bottle_cerberus.py
setup.py
bottle_cerberus.egg-info/PKG-INFO
bottle_cerberus.egg-info/SOURCES.txt
bottle_cerberus.egg-info/dependency_links.txt
bottle_cerberus.egg-info/not-zip-safe
bottle_cerberus.egg-info/requires.txt
bottle_cerberus.egg-info/top_level.txt