Metadata-Version: 1.1
Name: bottle-cerberus
Version: 1.1.3
Summary: Cerberus plugin for bottle
Home-page: https://github.com/agalera/bottle-cerberus
Author: Alberto Galera Jimenez
Author-email: galerajimenez@gmail.com
License: GPL
Keywords: bottle-cerberus
Platform: UNKNOWN
Classifier: Development Status :: 4 - Beta
Classifier: Topic :: Software Development :: Libraries :: Python Modules
Classifier: Intended Audience :: Developers
Classifier: License :: OSI Approved :: GNU General Public License (GPL)
Classifier: Natural Language :: English
Classifier: Programming Language :: Python :: 3
